Workbook

Sheet Summary
A1: OpenAI & Anthropic - 2030 revenue framework (bottom-up vs compute vs momentum)
A2: All cells are links to the company sheets (green). Edit assumptions on Inputs (Custom column).
A4: Metric ($B) | B4: Bear | C4: Base | D4: Bull | E4: Custom
A5: OpenAI - bottom-up revenue 2030 | B5: =OpenAI!C27 -> 95.810644 | C5: =OpenAI!D27 -> 297.655 | D5: =OpenAI!E27 -> 714.324 | E5: =OpenAI!F27 -> 297.655
A6: OpenAI - supply-side capacity 2030 | B6: =OpenAI!C36 -> 95.04 | C6: =OpenAI!D36 -> 296.8064 | D6: =OpenAI!E36 -> 1401.7536 | E6: =OpenAI!F36 -> 296.8064
A7: OpenAI - momentum exit-2030 run-rate | B7: =OpenAI!C47 -> 116.53824 | C7: =OpenAI!D47 -> 274.05 | D7: =OpenAI!E47 -> 407.28188 | E7: =OpenAI!F47 -> 274.05
A8: OpenAI - $/GW needed for bottom-up | B8: =OpenAI!C40 -> 6.3873763 | C8: =OpenAI!D40 -> 13.529773 | D8: =OpenAI!E40 -> 23.8108 | E8: =OpenAI!F40 -> 13.529773
A9: Anthropic - bottom-up revenue 2030 | B9: =Anthropic!C27 -> 82.332124 | C9: =Anthropic!D27 -> 259.416 | D9: =Anthropic!E27 -> 567.71136 | E9: =Anthropic!F27 -> 259.416
A10: Anthropic - supply-side capacity 2030 | B10: =Anthropic!C36 -> 63.36 | C10: =Anthropic!D36 -> 215.8592 | D10: =Anthropic!E36 -> 1027.9526 | E10: =Anthropic!F36 -> 215.8592
A11: Anthropic - momentum exit-2030 run-rate | B11: =Anthropic!C47 -> 162.21901 | C11: =Anthropic!D47 -> 346.086 | D11: =Anthropic!E47 -> 582.4 | E11: =Anthropic!F47 -> 346.086
A12: Anthropic - $/GW needed for bottom-up | B12: =Anthropic!C40 -> 8.2332124 | C12: =Anthropic!D40 -> 16.2135 | D12: =Anthropic!E40 -> 25.805062 | E12: =Anthropic!F40 -> 16.2135
A13: Combined bottom-up revenue 2030 | B13: =B5+B9 -> 178.14277 | C13: =C5+C9 -> 557.071 | D13: =D5+D9 -> 1282.0354 | E13: =E5+E9 -> 557.071
A15: Reference points (2026)
A16: OpenAI run-rate Aug-2026 | B16: 40 | C16: press reports; enterprise >50% of mix
A17: Anthropic run-rate end-Jul-2026 | B17: 65 | C17: Bloomberg/Axios 17-Aug-2026
A18: OpenAI company plan 2030 | B18: 280 | C18: >$280B (Bloomberg 20-Feb-2026); later reports up to ~$350B
A19: Anthropic company plan 2028 | B19: 195 | C19: $190-200B (Reuters 14-Aug-2026)
A20: Superforecaster median, OpenAI+Anthropic combined 2030 run-rate | B20: 300 | C20: Forecasting Research Institute; 34% prob. >$400B
A21: Bain: AI revenue needed by 2030 (whole industry) | B21: 2000 | C21: Bain Global Technology Report 2025

Sheet Inputs
A1: Inputs - 2030 assumptions (bear / base / bull) + Custom scenario
A2: Legend: blue = hardcoded input; yellow Custom column (G) is the one to edit - it defaults to Base. All formulas on the other sheets read this sheet. Anchors are 2026 observed data points (see Sources).
A4: Key | B4: Assumption (2030 unless stated) | C4: Unit | D4: Bear | E4: Base | F4: Bull | G4: Custom (edit) | H4: 2026 anchor / rationale
A5: Pool
A6: kw_dev | B6: Developers / data-AI engineers (M) | C6: M people | D6: 34 | E6: 38 | F6: 44 | G6: 38 | H6: ~30M professional devs 2026 (SlashData/Evans est.); AI-native builders expand the pool
A7: kw_pro | B7: Professional / high-intensity knowledge workers (M) | C7: M people | D7: 205 | E7: 220 | F7: 240 | G7: 220 | H7: finance, legal, consulting, research, marketing, sales, product; ~20% of ~1.05B KW
A8: kw_gen | B8: General knowledge workers (M) | C8: M people | D8: 770 | E8: 790 | F8: 815 | G8: 790 | H8: ~1B+ knowledge workers globally (Gartner >1B; Forrester 1.25B info workers); residual
A9: sal_dev | B9: Avg salary - developers ($k/yr, global blend) | C9: $k/yr | D9: 72 | E9: 75 | F9: 80 | G9: 75 | H9: US ~$150k, India ~$15k; global blend ~$75k
A10: sal_pro | B10: Avg salary - professionals ($k/yr, global blend) | C10: $k/yr | D10: 57 | E10: 60 | F10: 65 | G10: 60 | H10: global blend; US-only ~$100-120k
A11: sal_gen | B11: Avg salary - general KW ($k/yr, global blend) | C11: $k/yr | D11: 29 | E11: 30 | F11: 32 | G11: 30 | H11: global blend incl. EM
A12: Penetration
A13: pen_dev | B13: Paid-AI penetration - developers | C13: % | D13: 0.68 | E13: 0.8 | F13: 0.9 | G13: 0.8 | H13: 2026: ~10-12M paid (GitHub Copilot 4.7M, Cursor, Claude Code, Codex) of ~30M = ~35-40%
A14: pen_pro | B14: Paid-AI penetration - professionals | C14: % | D14: 0.32 | E14: 0.45 | F14: 0.55 | G14: 0.45 | H14: 2026: ~35-40M paid seats globally (M365 Copilot 20M, ChatGPT biz 9M, Claude, Gemini) = ~4% of all KW, ~10% of pros
A15: pen_gen | B15: Paid-AI penetration - general KW | C15: % | D15: 0.14 | E15: 0.25 | F15: 0.38 | G15: 0.25 | H15: seat-type products ($20-30/mo); Copilot bundling drives this
A16: Spend
A17: ratio_dev | B17: AI spend / salary - developers | C17: % | D17: 0.07 | E17: 0.13 | F17: 0.16 | G17: 0.13 | H17: 2026: Claude Code enterprise avg $150-250/mo = $1.8-3k/yr = 2-4% of global-blend salary; heavy agent users >$1k/mo
A18: ratio_pro | B18: AI spend / salary - professionals | C18: % | D18: 0.015 | E18: 0.03 | F18: 0.045 | G18: 0.03 | H18: 2026: M365 Copilot $360/yr; ChatGPT Enterprise ~$600-900/yr incl. usage; Atlanta Fed avg AI spend/employee $2,068 (all AI)
A19: ratio_gen | B19: AI spend / salary - general KW | C19: % | D19: 0.007 | E19: 0.012 | F19: 0.02 | G19: 0.012 | H19: 2026: Copilot $360/yr; ChatGPT Business $25-30/seat
A20: Share
A21: sh_dev_ant | B21: Anthropic share - developer spend | C21: % | D21: 0.35 | E21: 0.42 | F21: 0.48 | G21: 0.42 | H21: 2026: Claude Code $8B ARR (May-26) + Claude inside Cursor/Copilot; Menlo Ventures: Anthropic ~54% of coding model spend (2025)
A22: sh_dev_oai | B22: OpenAI share - developer spend | C22: % | D22: 0.18 | E22: 0.25 | F22: 0.32 | G22: 0.25 | H22: Codex 2M+ weekly users (Mar-26); GPT-5.x in Cursor/Copilot
A23: sh_pro_ant | B23: Anthropic share - professional seats | C23: % | D23: 0.13 | E23: 0.2 | F23: 0.24 | G23: 0.2 | H23: Claude Enterprise/Team/Cowork + Bedrock/Vertex/Foundry; MSFT/Google own the seat bundles
A24: sh_pro_oai | B24: OpenAI share - professional seats | C24: % | D24: 0.25 | E24: 0.3 | F24: 0.35 | G24: 0.3 | H24: 2026: 7M enterprise seats, 9M paying business users, >1M business customers
A25: sh_gen_ant | B25: Anthropic share - general seats | C25: % | D25: 0.06 | E25: 0.08 | F25: 0.12 | G25: 0.08 | H25: mostly model-layer share of Copilot-type bundles
A26: sh_gen_oai | B26: OpenAI share - general seats | C26: % | D26: 0.2 | E26: 0.25 | F26: 0.3 | G26: 0.25 | H26: ChatGPT Business/Edu; Copilot uses OpenAI models (rev share)
A27: Machine
A28: auto_pool | B28: Labour cost pool of AI-automatable digital tasks ($T) | C28: $T | D28: 7 | E28: 8 | F28: 10 | G28: 8 | H28: global labour comp ~$58T (2025); knowledge-work comp $35-50T; ~15-20% is task-automatable (support, back-office, docs, content, SDR, IT ops)
A29: auto_share | B29: Share of that pool automated by AI agents in 2030 | C29: % | D29: 0.06 | E29: 0.1 | F29: 0.14 | G29: 0.1 | H29: 2026: customer-service and coding agents are the only scaled cases
A30: auto_capture | B30: Vendor capture ($ AI spend per $ labour displaced) | C30: % | D30: 0.2 | E30: 0.25 | F30: 0.3 | G30: 0.25 | H30: Claude Code $2-3k/yr vs $20-40k of dev output = ~10%; SaaS captures 10-30% of value
A31: sh_auto_ant | B31: Anthropic share - machine API | C31: % | D31: 0.3 | E31: 0.38 | F31: 0.4 | G31: 0.38 | H31: Menlo Ventures 2025: Anthropic ~32-40% of enterprise LLM API spend, OpenAI ~25%
A32: sh_auto_oai | B32: OpenAI share - machine API | C32: % | D32: 0.2 | E32: 0.25 | F32: 0.28 | G32: 0.25 | H32: API ~15-20% of OpenAI revenue (2026); 15B tokens/min (Mar-26)
A33: Consumer OAI
A34: oai_mau | B34: ChatGPT MAU 2030 (M) | C34: M people | D34: 1500 | E34: 2000 | F34: 2500 | G34: 2000 | H34: 1B MAU (Jun-26), ~1B WAU (Jul-26); internet users ~5.6B->6B; Meta DAP 3.58B
A35: oai_conv | B35: Paid conversion (subs / MAU) | C35: % | D35: 0.045 | E35: 0.06 | F35: 0.09 | G35: 0.06 | H35: >50M consumer subs / ~1B = ~5% (Aug-26); India Go free promo dilutes
A36: oai_arpu | B36: Paid ARPU ($/month, blended) | C36: $/mo | D36: 15 | E36: 18 | F36: 24 | G36: 18 | H36: Go $8 (US)/Rs399 (India), Plus $20, Pro $200 (~0.5M subs); blended est. $25-30 in 2026, skewing down with EM mix
A37: oai_ad_arpu | B37: Ads ARPU per FREE user ($/yr) | C37: $/yr | D37: 15 | E37: 30 | F37: 55 | G37: 30 | H37: Meta ARPP 2025 $58 global (US&C ~$250+); Google Search ~$60-70/user; OpenAI plan $100B ads by 2030 = ~$50/free user; ads $1B run-rate <200 days after Feb-26 launch
A38: oai_gmv | B38: Commerce GMV routed via ChatGPT ($B) | C38: $B | D38: 100 | E38: 400 | F38: 1000 | G38: 400 | H38: Instant Checkout (Sep-25); global e-commerce ~$7T by 2030
A39: oai_take | B39: Commerce take rate | C39: % | D39: 0.02 | E39: 0.025 | F39: 0.03 | G39: 0.025 | H39: affiliate/checkout take rates 2-4%
A40: Consumer ANT
A41: ant_mau | B41: Claude consumer MAU 2030 (M) | C41: M people | D41: 150 | E41: 250 | F41: 400 | G41: 250 | H41: 2026 est. 30-140M (third-party, unreliable); consumer ~5-10% of revenue
A42: ant_conv | B42: Paid conversion (subs / MAU) | C42: % | D42: 0.08 | E42: 0.1 | F42: 0.13 | G42: 0.1 | H42: professional skew; Max tiers
A43: ant_arpu | B43: Paid ARPU ($/month, blended) | C43: $/mo | D43: 26 | E43: 32 | F43: 40 | G43: 32 | H43: Pro $20, Max $100/$200
A44: Other
A45: oai_other | B45: OpenAI other (devices, licensing, gov, media) ($B) | C45: $B | D45: 4 | E45: 10 | F45: 20 | G45: 10 | H45: io hardware, Sora, sovereign deals, MSFT rev share
A46: ant_other | B46: Anthropic other (gov/sovereign, licensing, reseller minimums) ($B) | C46: $B | D46: 4 | E46: 8 | F46: 15 | G46: 8 | H46: defense/gov, Amazon/Alexa, Apple
A47: Supply
A48: oai_gw | B48: OpenAI GW online (avg 2030) | C48: GW | D48: 15 | E48: 22 | F48: 30 | G48: 22 | H48: 1.9GW end-25; 30GW target by 2030; 8GW+ of 10GW Stargate secured; Oracle 4.5GW from 2027; Nvidia 10GW, AMD 6GW, Broadcom 10GW LOIs
A49: ant_gw | B49: Anthropic GW online (avg 2030) | C49: GW | D49: 10 | E49: 16 | F49: 22 | G49: 16 | H49: ~5GW end-26, ~10GW 2027 (press); Google/Broadcom 3.5GW TPU from 2027; AWS up to 5GW Trainium; Australia 2.16GW (2027)
A50: inf_share | B50: Inference share of GW | C50: % | D50: 0.55 | E50: 0.62 | F50: 0.72 | G50: 0.62 | H50: 2025-26 fleets ~40-50% training/research; shifts to inference as revenue scales
A51: util | B51: Inference fleet utilisation | C51: % | D51: 0.6 | E51: 0.68 | F51: 0.78 | G51: 0.68 | H51: peak/off-peak; batch jobs fill valleys
A52: tok_per_gw | B52: Tokens per GW-year at 100% util (quadrillion) | C52: 1e15 tokens | D52: 16 | E52: 20 | F52: 32 | G52: 20 | H52: OpenAI 2026: ~15-20 quadrillion tok/yr on ~1.5-2GW inference => ~10 at actual util; Google 38 quadrillion/yr (3.2q/mo, May-26); GB200 frontier config 75-85q/GW (vendor claim), Rubin 2-4x GB300
A53: price_tok | B53: Realised blended price ($/M tokens, 2030) | C53: $/M | D53: 1.2 | E53: 1.6 | F53: 2.6 | G53: 1.6 | H53: 2026 realised: OpenAI ~$2-2.5/M (subs incl.), Anthropic ~$5/M (API-heavy); list Opus $4/$20, GPT $2/$10; ~10x/yr deflation per unit capability offset by mix
A54: Momentum
A55: oai_rr26 | B55: OpenAI exit-2026 run-rate ($B) | C55: $B | D55: 46 | E55: 50 | F55: 55 | G55: 50 | H55: >$40B run-rate Aug-26 (+35% QTD)
A56: ant_rr26 | B56: Anthropic exit-2026 run-rate ($B) | C56: $B | D56: 80 | E56: 90 | F56: 100 | G56: 90 | H56: $65B run-rate end-Jul-26; $47B mid-May; $30B Apr; $14B Feb; $9B Dec-25
A57: oai_g27 | B57: OpenAI growth 2027 | C57: % | D57: 0.45 | E57: 0.75 | F57: 0.95 | G57: 0.75 | H57: company plan implies ~60-80%/yr
A58: oai_g28 | B58: OpenAI growth 2028 | C58: % | D58: 0.3 | E58: 0.6 | F58: 0.75 | G58: 0.6
A59: oai_g29 | B59: OpenAI growth 2029 | C59: % | D59: 0.2 | E59: 0.45 | F59: 0.55 | G59: 0.45
A60: oai_g30 | B60: OpenAI growth 2030 | C60: % | D60: 0.12 | E60: 0.35 | F60: 0.4 | G60: 0.35
A61: ant_g27 | B61: Anthropic growth 2027 | C61: % | D61: 0.4 | E61: 0.7 | F61: 1 | G61: 0.7 | H61: internal p50 May-27 run-rate $138B (third-party cite)
A62: ant_g28 | B62: Anthropic growth 2028 | C62: % | D62: 0.22 | E62: 0.45 | F62: 0.6 | G62: 0.45 | H62: IPO case: $190-200B revenue 2028 (Reuters, Aug-26)
A63: ant_g29 | B63: Anthropic growth 2029 | C63: % | D63: 0.12 | E63: 0.3 | F63: 0.4 | G63: 0.3
A64: ant_g30 | B64: Anthropic growth 2030 | C64: % | D64: 0.06 | E64: 0.2 | F64: 0.3 | G64: 0.2

Sheet OpenAI
A1: OpenAI - 2030 revenue, bottom-up ($B unless stated)
A2: Green = link to Inputs; black = formula; blue = hardcoded (2026 mix estimates, targets, constants).
A4: Line | B4: Unit | C4: Bear | D4: Base | E4: Bull | F4: Custom | G4: Formula / note
A5: Global pools (all vendors) - shared with the other company
A6: Spend per paid seat - developers | B6: $/yr | C6: =Inputs!$D$9*Inputs!$D$17*1000 -> 5040 | D6: =Inputs!$E$9*Inputs!$E$17*1000 -> 9750 | E6: =Inputs!$F$9*Inputs!$F$17*1000 -> 12800 | F6: =Inputs!$G$9*Inputs!$G$17*1000 -> 9750 | G6: salary x AI spend ratio
A7: Spend per paid seat - professionals | B7: $/yr | C7: =Inputs!$D$10*Inputs!$D$18*1000 -> 855 | D7: =Inputs!$E$10*Inputs!$E$18*1000 -> 1800 | E7: =Inputs!$F$10*Inputs!$F$18*1000 -> 2925 | F7: =Inputs!$G$10*Inputs!$G$18*1000 -> 1800
A8: Spend per paid seat - general KW | B8: $/yr | C8: =Inputs!$D$11*Inputs!$D$19*1000 -> 203 | D8: =Inputs!$E$11*Inputs!$E$19*1000 -> 360 | E8: =Inputs!$F$11*Inputs!$F$19*1000 -> 640 | F8: =Inputs!$G$11*Inputs!$G$19*1000 -> 360
A9: Paid developer seats | B9: M | C9: =Inputs!$D$6*Inputs!$D$13 -> 23.12 | D9: =Inputs!$E$6*Inputs!$E$13 -> 30.4 | E9: =Inputs!$F$6*Inputs!$F$13 -> 39.6 | F9: =Inputs!$G$6*Inputs!$G$13 -> 30.4 | G9: workers x penetration
A10: Paid professional seats | B10: M | C10: =Inputs!$D$7*Inputs!$D$14 -> 65.6 | D10: =Inputs!$E$7*Inputs!$E$14 -> 99 | E10: =Inputs!$F$7*Inputs!$F$14 -> 132 | F10: =Inputs!$G$7*Inputs!$G$14 -> 99
A11: Paid general KW seats | B11: M | C11: =Inputs!$D$8*Inputs!$D$15 -> 107.8 | D11: =Inputs!$E$8*Inputs!$E$15 -> 197.5 | E11: =Inputs!$F$8*Inputs!$F$15 -> 309.7 | F11: =Inputs!$G$8*Inputs!$G$15 -> 197.5
A12: Developer AI spend pool | B12: $B | C12: =C9*C6/1000 -> 116.5248 | D12: =D9*D6/1000 -> 296.4 | E12: =E9*E6/1000 -> 506.88 | F12: =F9*F6/1000 -> 296.4 | G12: seats (M) x $/seat / 1000
A13: Professional AI spend pool | B13: $B | C13: =C10*C7/1000 -> 56.088 | D13: =D10*D7/1000 -> 178.2 | E13: =E10*E7/1000 -> 386.1 | F13: =F10*F7/1000 -> 178.2
A14: General KW AI spend pool | B14: $B | C14: =C11*C8/1000 -> 21.8834 | D14: =D11*D8/1000 -> 71.1 | E14: =E11*E8/1000 -> 198.208 | F14: =F11*F8/1000 -> 71.1
A15: Machine / agent API pool | B15: $B | C15: =Inputs!$D$28*Inputs!$D$29*Inputs!$D$30*1000 -> 84 | D15: =Inputs!$E$28*Inputs!$E$29*Inputs!$E$30*1000 -> 200 | E15: =Inputs!$F$28*Inputs!$F$29*Inputs!$F$30*1000 -> 420 | F15: =Inputs!$G$28*Inputs!$G$29*Inputs!$G$30*1000 -> 200 | G15: labour pool ($T) x automated share x vendor capture
A16: Total enterprise AI pool (all vendors) | B16: $B | C16: =SUM(C12:C15) -> 278.4962 | D16: =SUM(D12:D15) -> 745.7 | E16: =SUM(E12:E15) -> 1511.188 | F16: =SUM(F12:F15) -> 745.7
A18: OpenAI revenue 2030 by segment
A19: Developers / coding agents | B19: $B | C19: =C12*Inputs!$D$22 -> 20.974464 | D19: =D12*Inputs!$E$22 -> 74.1 | E19: =E12*Inputs!$F$22 -> 162.2016 | F19: =F12*Inputs!$G$22 -> 74.1 | G19: pool x company share
A20: Professional seats | B20: $B | C20: =C13*Inputs!$D$24 -> 14.022 | D20: =D13*Inputs!$E$24 -> 53.46 | E20: =E13*Inputs!$F$24 -> 135.135 | F20: =F13*Inputs!$G$24 -> 53.46
A21: General KW seats | B21: $B | C21: =C14*Inputs!$D$26 -> 4.37668 | D21: =D14*Inputs!$E$26 -> 17.775 | E21: =E14*Inputs!$F$26 -> 59.4624 | F21: =F14*Inputs!$G$26 -> 17.775
A22: Machine / agent API | B22: $B | C22: =C15*Inputs!$D$32 -> 16.8 | D22: =D15*Inputs!$E$32 -> 50 | E22: =E15*Inputs!$F$32 -> 117.6 | F22: =F15*Inputs!$G$32 -> 50
A23: Consumer subscriptions | B23: $B | C23: =Inputs!$D$34*Inputs!$D$35*Inputs!$D$36*12/1000 -> 12.15 | D23: =Inputs!$E$34*Inputs!$E$35*Inputs!$E$36*12/1000 -> 25.92 | E23: =Inputs!$F$34*Inputs!$F$35*Inputs!$F$36*12/1000 -> 64.8 | F23: =Inputs!$G$34*Inputs!$G$35*Inputs!$G$36*12/1000 -> 25.92 | G23: MAU x paid conversion x ARPU x 12
A24: Consumer ads | B24: $B | C24: =Inputs!$D$34*(1-Inputs!$D$35)*Inputs!$D$37/1000 -> 21.4875 | D24: =Inputs!$E$34*(1-Inputs!$E$35)*Inputs!$E$37/1000 -> 56.4 | E24: =Inputs!$F$34*(1-Inputs!$F$35)*Inputs!$F$37/1000 -> 125.125 | F24: =Inputs!$G$34*(1-Inputs!$G$35)*Inputs!$G$37/1000 -> 56.4 | G24: free MAU x ads ARPU
A25: Commerce / agentic transactions | B25: $B | C25: =Inputs!$D$38*Inputs!$D$39 -> 2 | D25: =Inputs!$E$38*Inputs!$E$39 -> 10 | E25: =Inputs!$F$38*Inputs!$F$39 -> 30 | F25: =Inputs!$G$38*Inputs!$G$39 -> 10 | G25: GMV x take rate
A26: Other | B26: $B | C26: =Inputs!$D$45 -> 4 | D26: =Inputs!$E$45 -> 10 | E26: =Inputs!$F$45 -> 20 | F26: =Inputs!$G$45 -> 10
A27: TOTAL REVENUE 2030 | B27: $B | C27: =SUM(C19:C26) -> 95.810644 | D27: =SUM(D19:D26) -> 297.655 | E27: =SUM(E19:E26) -> 714.324 | F27: =SUM(F19:F26) -> 297.655
A28: Enterprise subtotal (4 engines) | B28: $B | C28: =SUM(C19:C22) -> 56.173144 | D28: =SUM(D19:D22) -> 195.335 | E28: =SUM(E19:E22) -> 474.399 | F28: =SUM(F19:F22) -> 195.335
A29: Consumer subtotal | B29: $B | C29: =SUM(C23:C25) -> 35.6375 | D29: =SUM(D23:D25) -> 92.32 | E29: =SUM(E23:E25) -> 219.925 | F29: =SUM(F23:F25) -> 92.32
A30: Enterprise share of revenue | B30: % | C30: =IF(C27=0,0,C28/C27) -> 0.58629336 | D30: =IF(D27=0,0,D28/D27) -> 0.65624633 | E30: =IF(E27=0,0,E28/E27) -> 0.664123 | F30: =IF(F27=0,0,F28/F27) -> 0.65624633
A32: Supply-side check (compute)
A33: GW online (avg 2030) | B33: GW | C33: =Inputs!$D$48 -> 15 | D33: =Inputs!$E$48 -> 22 | E33: =Inputs!$F$48 -> 30 | F33: =Inputs!$G$48 -> 22
A34: Revenue per GW of inference | B34: $B/GW | C34: =Inputs!$D$52*Inputs!$D$53*Inputs!$D$51 -> 11.52 | D34: =Inputs!$E$52*Inputs!$E$53*Inputs!$E$51 -> 21.76 | E34: =Inputs!$F$52*Inputs!$F$53*Inputs!$F$51 -> 64.896 | F34: =Inputs!$G$52*Inputs!$G$53*Inputs!$G$51 -> 21.76 | G34: tokens/GW (1e15) x $/M tokens x utilisation
A35: Revenue per GW of TOTAL capacity | B35: $B/GW | C35: =C34*Inputs!$D$50 -> 6.336 | D35: =D34*Inputs!$E$50 -> 13.4912 | E35: =E34*Inputs!$F$50 -> 46.72512 | F35: =F34*Inputs!$G$50 -> 13.4912 | G35: x inference share of fleet
A36: Supply-side revenue capacity | B36: $B | C36: =C33*C35 -> 95.04 | D36: =D33*D35 -> 296.8064 | E36: =E33*E35 -> 1401.7536 | F36: =F33*F35 -> 296.8064 | G36: GW x $/GW
A37: Demand-side revenue (bottom-up) | B37: $B | C37: =C27 -> 95.810644 | D37: =D27 -> 297.655 | E37: =E27 -> 714.324 | F37: =F27 -> 297.655
A38: Demand / supply capacity | B38: x | C38: =IF(C36=0,0,C37/C36) -> 1.0081086 | D38: =IF(D36=0,0,D37/D36) -> 1.0028591 | E38: =IF(E36=0,0,E37/E36) -> 0.50959313 | F38: =IF(F36=0,0,F37/F36) -> 1.0028591 | G38: >1.0x = compute-constrained
A39: GW needed for demand at this $/GW | B39: GW | C39: =IF(C35=0,0,C37/C35) -> 15.121629 | D39: =IF(D35=0,0,D37/D35) -> 22.0629 | E39: =IF(E35=0,0,E37/E35) -> 15.287794 | F39: =IF(F35=0,0,F37/F35) -> 22.0629
A40: $/GW needed for demand at this GW | B40: $B/GW | C40: =IF(C33=0,0,C37/C33) -> 6.3873763 | D40: =IF(D33=0,0,D37/D33) -> 13.529773 | E40: =IF(E33=0,0,E37/E33) -> 23.8108 | F40: =IF(F33=0,0,F37/F33) -> 13.529773
A42: Momentum path (annualised run-rate)
A43: Exit-2026 run-rate | B43: $B | C43: =Inputs!$D$55 -> 46 | D43: =Inputs!$E$55 -> 50 | E43: =Inputs!$F$55 -> 55 | F43: =Inputs!$G$55 -> 50
A44: Exit-2027 run-rate | B44: $B | C44: =C43*(1+Inputs!$D$57) -> 66.7 | D44: =D43*(1+Inputs!$E$57) -> 87.5 | E44: =E43*(1+Inputs!$F$57) -> 107.25 | F44: =F43*(1+Inputs!$G$57) -> 87.5 | G44: x (1 + growth 2027)
A45: Exit-2028 run-rate | B45: $B | C45: =C44*(1+Inputs!$D$58) -> 86.71 | D45: =D44*(1+Inputs!$E$58) -> 140 | E45: =E44*(1+Inputs!$F$58) -> 187.6875 | F45: =F44*(1+Inputs!$G$58) -> 140 | G45: x (1 + growth 2028)
A46: Exit-2029 run-rate | B46: $B | C46: =C45*(1+Inputs!$D$59) -> 104.052 | D46: =D45*(1+Inputs!$E$59) -> 203 | E46: =E45*(1+Inputs!$F$59) -> 290.91562 | F46: =F45*(1+Inputs!$G$59) -> 203 | G46: x (1 + growth 2029)
A47: Exit-2030 run-rate | B47: $B | C47: =C46*(1+Inputs!$D$60) -> 116.53824 | D47: =D46*(1+Inputs!$E$60) -> 274.05 | E47: =E46*(1+Inputs!$F$60) -> 407.28188 | F47: =F46*(1+Inputs!$G$60) -> 274.05 | G47: x (1 + growth 2030)
A48: Bottom-up 2030 / momentum exit-2030 | B48: x | C48: =IF(C47=0,0,C27/C47) -> 0.8221391 | D48: =IF(D47=0,0,D27/D47) -> 1.0861339 | E48: =IF(E47=0,0,E27/E47) -> 1.7538811 | F48: =IF(F47=0,0,F27/F47) -> 1.0861339 | G48: <1.0x = bottom-up is below the run-rate path
A50: Bridge: 2026 run-rate mix (est., $B) -> 2030 (multiple per scenario; CAGR on Base)
A51: Segment | B51: 2026 RR est. | C51: Bear x | D51: Base x | E51: Bull x | F51: Custom x | G51: CAGR (Base, 4.33 yrs)
A52: Developers / coding agents | B52: 4 | C52: =IF($B52=0,"n/a",C19/$B52) -> 5.243616 | D52: =IF($B52=0,"n/a",D19/$B52) -> 18.525 | E52: =IF($B52=0,"n/a",E19/$B52) -> 40.5504 | F52: =IF($B52=0,"n/a",F19/$B52) -> 18.525 | G52: =IF($B52=0,"n/a",(D19/$B52)^(1/4.33)-1) -> 0.96238767
A53: Professional seats | B53: 8 | C53: =IF($B53=0,"n/a",C20/$B53) -> 1.75275 | D53: =IF($B53=0,"n/a",D20/$B53) -> 6.6825 | E53: =IF($B53=0,"n/a",E20/$B53) -> 16.891875 | F53: =IF($B53=0,"n/a",F20/$B53) -> 6.6825 | G53: =IF($B53=0,"n/a",(D20/$B53)^(1/4.33)-1) -> 0.55066178
A54: General KW seats | B54: 2 | C54: =IF($B54=0,"n/a",C21/$B54) -> 2.18834 | D54: =IF($B54=0,"n/a",D21/$B54) -> 8.8875 | E54: =IF($B54=0,"n/a",E21/$B54) -> 29.7312 | F54: =IF($B54=0,"n/a",F21/$B54) -> 8.8875 | G54: =IF($B54=0,"n/a",(D21/$B54)^(1/4.33)-1) -> 0.65621874
A55: Machine / agent API | B55: 6 | C55: =IF($B55=0,"n/a",C22/$B55) -> 2.8 | D55: =IF($B55=0,"n/a",D22/$B55) -> 8.3333333 | E55: =IF($B55=0,"n/a",E22/$B55) -> 19.6 | F55: =IF($B55=0,"n/a",F22/$B55) -> 8.3333333 | G55: =IF($B55=0,"n/a",(D22/$B55)^(1/4.33)-1) -> 0.63177479
A56: Consumer subscriptions | B56: 17 | C56: =IF($B56=0,"n/a",C23/$B56) -> 0.71470588 | D56: =IF($B56=0,"n/a",D23/$B56) -> 1.5247059 | E56: =IF($B56=0,"n/a",E23/$B56) -> 3.8117647 | F56: =IF($B56=0,"n/a",F23/$B56) -> 1.5247059 | G56: =IF($B56=0,"n/a",(D23/$B56)^(1/4.33)-1) -> 0.10231636
A57: Consumer ads | B57: 1 | C57: =IF($B57=0,"n/a",C24/$B57) -> 21.4875 | D57: =IF($B57=0,"n/a",D24/$B57) -> 56.4 | E57: =IF($B57=0,"n/a",E24/$B57) -> 125.125 | F57: =IF($B57=0,"n/a",F24/$B57) -> 56.4 | G57: =IF($B57=0,"n/a",(D24/$B57)^(1/4.33)-1) -> 1.5377711
A58: Commerce / agentic transactions | B58: 0.5 | C58: =IF($B58=0,"n/a",C25/$B58) -> 4 | D58: =IF($B58=0,"n/a",D25/$B58) -> 20 | E58: =IF($B58=0,"n/a",E25/$B58) -> 60 | F58: =IF($B58=0,"n/a",F25/$B58) -> 20 | G58: =IF($B58=0,"n/a",(D25/$B58)^(1/4.33)-1) -> 0.99741736
A59: Other | B59: 1.5 | C59: =IF($B59=0,"n/a",C26/$B59) -> 2.6666667 | D59: =IF($B59=0,"n/a",D26/$B59) -> 6.6666667 | E59: =IF($B59=0,"n/a",E26/$B59) -> 13.333333 | F59: =IF($B59=0,"n/a",F26/$B59) -> 6.6666667 | G59: =IF($B59=0,"n/a",(D26/$B59)^(1/4.33)-1) -> 0.54981248
A60: TOTAL | B60: =SUM(B52:B59) -> 40 | C60: =C27/$B60 -> 2.3952661 | D60: =D27/$B60 -> 7.441375 | E60: =E27/$B60 -> 17.8581 | F60: =F27/$B60 -> 7.441375 | G60: =(D27/$B60)^(1/4.33)-1 -> 0.58966491 | H60: 2026 mix is our estimate from disclosed run-rates (blue = editable)
A62: What you need to believe (targets vs Base structure)
A63: Target revenue 2030 ($B) | B63: input | C63: 350 | D63: 400
A64: Implied $/GW (total) at Base GW | C64: =C$63/$D$33 -> 15.909091 | D64: =D$63/$D$33 -> 18.181818 | G64: target / Base GW
A65: Implied GW at $/GW = | B65: 35 | C65: =C$63/$B65 -> 10 | D65: =D$63/$B65 -> 11.428571 | G65: the deck's $35B/GW assumption (editable)
A66: Implied GW at Base $/GW | C66: =C$63/$D$35 -> 25.942837 | D66: =D$63/$D$35 -> 29.648956
A67: Required uplift on enterprise engines vs Base | C67: =(C$63-($D$27-$D$28))/$D$28 -> 1.2679755 | D67: =(D$63-($D$27-$D$28))/$D$28 -> 1.523946 | G67: consumer + other held at Base
A68: ...if only developer spend/salary moves | C68: =Inputs!$E$17*(1+(C67-1)*$D$28/$D$19) -> 0.22183333 | D68: =Inputs!$E$17*(1+(D67-1)*$D$28/$D$19) -> 0.30955263 | G68: vs Base ratio on Inputs
A69: ...if only machine-API automated share moves | C69: =Inputs!$E$29*(1+(C67-1)*$D$28/$D$22) -> 0.20469 | D69: =Inputs!$E$29*(1+(D67-1)*$D$28/$D$22) -> 0.30469
A70: ...if only professional-seat penetration moves | C70: =Inputs!$E$14*(1+(C67-1)*$D$28/$D$20) -> 0.89061448 | D70: =Inputs!$E$14*(1+(D67-1)*$D$28/$D$20) -> 1.3114899 | G70: >100% = impossible
A71: Target as % of global enterprise AI pool (Base) | C71: =C$63/$D$16 -> 0.46935765 | D71: =D$63/$D$16 -> 0.53640874
A72: Target as % of global labour compensation ($B) = | B72: 65000 | C72: =C$63/$B72 -> 0.0053846154 | D72: =D$63/$B72 -> 0.0061538462 | G72: ~$58T 2025 growing to ~$65T
A73: Target as % of global software spend ($B) = | B73: 2400 | C73: =C$63/$B73 -> 0.14583333 | D73: =D$63/$B73 -> 0.16666667 | G73: Gartner $1.47T 2026 -> ~$2.4T 2030

Sheet Anthropic
A1: Anthropic - 2030 revenue, bottom-up ($B unless stated)
A2: Green = link to Inputs; black = formula; blue = hardcoded (2026 mix estimates, targets, constants).
A4: Line | B4: Unit | C4: Bear | D4: Base | E4: Bull | F4: Custom | G4: Formula / note
A5: Global pools (all vendors) - shared with the other company
A6: Spend per paid seat - developers | B6: $/yr | C6: =Inputs!$D$9*Inputs!$D$17*1000 -> 5040 | D6: =Inputs!$E$9*Inputs!$E$17*1000 -> 9750 | E6: =Inputs!$F$9*Inputs!$F$17*1000 -> 12800 | F6: =Inputs!$G$9*Inputs!$G$17*1000 -> 9750 | G6: salary x AI spend ratio
A7: Spend per paid seat - professionals | B7: $/yr | C7: =Inputs!$D$10*Inputs!$D$18*1000 -> 855 | D7: =Inputs!$E$10*Inputs!$E$18*1000 -> 1800 | E7: =Inputs!$F$10*Inputs!$F$18*1000 -> 2925 | F7: =Inputs!$G$10*Inputs!$G$18*1000 -> 1800
A8: Spend per paid seat - general KW | B8: $/yr | C8: =Inputs!$D$11*Inputs!$D$19*1000 -> 203 | D8: =Inputs!$E$11*Inputs!$E$19*1000 -> 360 | E8: =Inputs!$F$11*Inputs!$F$19*1000 -> 640 | F8: =Inputs!$G$11*Inputs!$G$19*1000 -> 360
A9: Paid developer seats | B9: M | C9: =Inputs!$D$6*Inputs!$D$13 -> 23.12 | D9: =Inputs!$E$6*Inputs!$E$13 -> 30.4 | E9: =Inputs!$F$6*Inputs!$F$13 -> 39.6 | F9: =Inputs!$G$6*Inputs!$G$13 -> 30.4 | G9: workers x penetration
A10: Paid professional seats | B10: M | C10: =Inputs!$D$7*Inputs!$D$14 -> 65.6 | D10: =Inputs!$E$7*Inputs!$E$14 -> 99 | E10: =Inputs!$F$7*Inputs!$F$14 -> 132 | F10: =Inputs!$G$7*Inputs!$G$14 -> 99
A11: Paid general KW seats | B11: M | C11: =Inputs!$D$8*Inputs!$D$15 -> 107.8 | D11: =Inputs!$E$8*Inputs!$E$15 -> 197.5 | E11: =Inputs!$F$8*Inputs!$F$15 -> 309.7 | F11: =Inputs!$G$8*Inputs!$G$15 -> 197.5
A12: Developer AI spend pool | B12: $B | C12: =C9*C6/1000 -> 116.5248 | D12: =D9*D6/1000 -> 296.4 | E12: =E9*E6/1000 -> 506.88 | F12: =F9*F6/1000 -> 296.4 | G12: seats (M) x $/seat / 1000
A13: Professional AI spend pool | B13: $B | C13: =C10*C7/1000 -> 56.088 | D13: =D10*D7/1000 -> 178.2 | E13: =E10*E7/1000 -> 386.1 | F13: =F10*F7/1000 -> 178.2
A14: General KW AI spend pool | B14: $B | C14: =C11*C8/1000 -> 21.8834 | D14: =D11*D8/1000 -> 71.1 | E14: =E11*E8/1000 -> 198.208 | F14: =F11*F8/1000 -> 71.1
A15: Machine / agent API pool | B15: $B | C15: =Inputs!$D$28*Inputs!$D$29*Inputs!$D$30*1000 -> 84 | D15: =Inputs!$E$28*Inputs!$E$29*Inputs!$E$30*1000 -> 200 | E15: =Inputs!$F$28*Inputs!$F$29*Inputs!$F$30*1000 -> 420 | F15: =Inputs!$G$28*Inputs!$G$29*Inputs!$G$30*1000 -> 200 | G15: labour pool ($T) x automated share x vendor capture
A16: Total enterprise AI pool (all vendors) | B16: $B | C16: =SUM(C12:C15) -> 278.4962 | D16: =SUM(D12:D15) -> 745.7 | E16: =SUM(E12:E15) -> 1511.188 | F16: =SUM(F12:F15) -> 745.7
A18: Anthropic revenue 2030 by segment
A19: Developers / coding agents | B19: $B | C19: =C12*Inputs!$D$21 -> 40.78368 | D19: =D12*Inputs!$E$21 -> 124.488 | E19: =E12*Inputs!$F$21 -> 243.3024 | F19: =F12*Inputs!$G$21 -> 124.488 | G19: pool x company share
A20: Professional seats | B20: $B | C20: =C13*Inputs!$D$23 -> 7.29144 | D20: =D13*Inputs!$E$23 -> 35.64 | E20: =E13*Inputs!$F$23 -> 92.664 | F20: =F13*Inputs!$G$23 -> 35.64
A21: General KW seats | B21: $B | C21: =C14*Inputs!$D$25 -> 1.313004 | D21: =D14*Inputs!$E$25 -> 5.688 | E21: =E14*Inputs!$F$25 -> 23.78496 | F21: =F14*Inputs!$G$25 -> 5.688
A22: Machine / agent API | B22: $B | C22: =C15*Inputs!$D$31 -> 25.2 | D22: =D15*Inputs!$E$31 -> 76 | E22: =E15*Inputs!$F$31 -> 168 | F22: =F15*Inputs!$G$31 -> 76
A23: Consumer subscriptions | B23: $B | C23: =Inputs!$D$41*Inputs!$D$42*Inputs!$D$43*12/1000 -> 3.744 | D23: =Inputs!$E$41*Inputs!$E$42*Inputs!$E$43*12/1000 -> 9.6 | E23: =Inputs!$F$41*Inputs!$F$42*Inputs!$F$43*12/1000 -> 24.96 | F23: =Inputs!$G$41*Inputs!$G$42*Inputs!$G$43*12/1000 -> 9.6 | G23: MAU x paid conversion x ARPU x 12
A24: Consumer ads | B24: $B | C24: =0 -> 0 | D24: =0 -> 0 | E24: =0 -> 0 | F24: =0 -> 0 | G24: Anthropic: no ads (stated policy) - hardcoded 0
A25: Commerce / agentic transactions | B25: $B | C25: =0 -> 0 | D25: =0 -> 0 | E25: =0 -> 0 | F25: =0 -> 0 | G25: not modelled - hardcoded 0
A26: Other | B26: $B | C26: =Inputs!$D$46 -> 4 | D26: =Inputs!$E$46 -> 8 | E26: =Inputs!$F$46 -> 15 | F26: =Inputs!$G$46 -> 8
A27: TOTAL REVENUE 2030 | B27: $B | C27: =SUM(C19:C26) -> 82.332124 | D27: =SUM(D19:D26) -> 259.416 | E27: =SUM(E19:E26) -> 567.71136 | F27: =SUM(F19:F26) -> 259.416
A28: Enterprise subtotal (4 engines) | B28: $B | C28: =SUM(C19:C22) -> 74.588124 | D28: =SUM(D19:D22) -> 241.816 | E28: =SUM(E19:E22) -> 527.75136 | F28: =SUM(F19:F22) -> 241.816
A29: Consumer subtotal | B29: $B | C29: =SUM(C23:C25) -> 3.744 | D29: =SUM(D23:D25) -> 9.6 | E29: =SUM(E23:E25) -> 24.96 | F29: =SUM(F23:F25) -> 9.6
A30: Enterprise share of revenue | B30: % | C30: =IF(C27=0,0,C28/C27) -> 0.90594194 | D30: =IF(D27=0,0,D28/D27) -> 0.9321553 | E30: =IF(E27=0,0,E28/E27) -> 0.92961212 | F30: =IF(F27=0,0,F28/F27) -> 0.9321553
A32: Supply-side check (compute)
A33: GW online (avg 2030) | B33: GW | C33: =Inputs!$D$49 -> 10 | D33: =Inputs!$E$49 -> 16 | E33: =Inputs!$F$49 -> 22 | F33: =Inputs!$G$49 -> 16
A34: Revenue per GW of inference | B34: $B/GW | C34: =Inputs!$D$52*Inputs!$D$53*Inputs!$D$51 -> 11.52 | D34: =Inputs!$E$52*Inputs!$E$53*Inputs!$E$51 -> 21.76 | E34: =Inputs!$F$52*Inputs!$F$53*Inputs!$F$51 -> 64.896 | F34: =Inputs!$G$52*Inputs!$G$53*Inputs!$G$51 -> 21.76 | G34: tokens/GW (1e15) x $/M tokens x utilisation
A35: Revenue per GW of TOTAL capacity | B35: $B/GW | C35: =C34*Inputs!$D$50 -> 6.336 | D35: =D34*Inputs!$E$50 -> 13.4912 | E35: =E34*Inputs!$F$50 -> 46.72512 | F35: =F34*Inputs!$G$50 -> 13.4912 | G35: x inference share of fleet
A36: Supply-side revenue capacity | B36: $B | C36: =C33*C35 -> 63.36 | D36: =D33*D35 -> 215.8592 | E36: =E33*E35 -> 1027.9526 | F36: =F33*F35 -> 215.8592 | G36: GW x $/GW
A37: Demand-side revenue (bottom-up) | B37: $B | C37: =C27 -> 82.332124 | D37: =D27 -> 259.416 | E37: =E27 -> 567.71136 | F37: =F27 -> 259.416
A38: Demand / supply capacity | B38: x | C38: =IF(C36=0,0,C37/C36) -> 1.2994338 | D38: =IF(D36=0,0,D37/D36) -> 1.2017834 | E38: =IF(E36=0,0,E37/E36) -> 0.55227385 | F38: =IF(F36=0,0,F37/F36) -> 1.2017834 | G38: >1.0x = compute-constrained
A39: GW needed for demand at this $/GW | B39: GW | C39: =IF(C35=0,0,C37/C35) -> 12.994338 | D39: =IF(D35=0,0,D37/D35) -> 19.228534 | E39: =IF(E35=0,0,E37/E35) -> 12.150025 | F39: =IF(F35=0,0,F37/F35) -> 19.228534
A40: $/GW needed for demand at this GW | B40: $B/GW | C40: =IF(C33=0,0,C37/C33) -> 8.2332124 | D40: =IF(D33=0,0,D37/D33) -> 16.2135 | E40: =IF(E33=0,0,E37/E33) -> 25.805062 | F40: =IF(F33=0,0,F37/F33) -> 16.2135
A42: Momentum path (annualised run-rate)
A43: Exit-2026 run-rate | B43: $B | C43: =Inputs!$D$56 -> 80 | D43: =Inputs!$E$56 -> 90 | E43: =Inputs!$F$56 -> 100 | F43: =Inputs!$G$56 -> 90
A44: Exit-2027 run-rate | B44: $B | C44: =C43*(1+Inputs!$D$61) -> 112 | D44: =D43*(1+Inputs!$E$61) -> 153 | E44: =E43*(1+Inputs!$F$61) -> 200 | F44: =F43*(1+Inputs!$G$61) -> 153 | G44: x (1 + growth 2027)
A45: Exit-2028 run-rate | B45: $B | C45: =C44*(1+Inputs!$D$62) -> 136.64 | D45: =D44*(1+Inputs!$E$62) -> 221.85 | E45: =E44*(1+Inputs!$F$62) -> 320 | F45: =F44*(1+Inputs!$G$62) -> 221.85 | G45: x (1 + growth 2028)
A46: Exit-2029 run-rate | B46: $B | C46: =C45*(1+Inputs!$D$63) -> 153.0368 | D46: =D45*(1+Inputs!$E$63) -> 288.405 | E46: =E45*(1+Inputs!$F$63) -> 448 | F46: =F45*(1+Inputs!$G$63) -> 288.405 | G46: x (1 + growth 2029)
A47: Exit-2030 run-rate | B47: $B | C47: =C46*(1+Inputs!$D$64) -> 162.21901 | D47: =D46*(1+Inputs!$E$64) -> 346.086 | E47: =E46*(1+Inputs!$F$64) -> 582.4 | F47: =F46*(1+Inputs!$G$64) -> 346.086 | G47: x (1 + growth 2030)
A48: Bottom-up 2030 / momentum exit-2030 | B48: x | C48: =IF(C47=0,0,C27/C47) -> 0.50753685 | D48: =IF(D47=0,0,D27/D47) -> 0.74957092 | E48: =IF(E47=0,0,E27/E47) -> 0.97477912 | F48: =IF(F47=0,0,F27/F47) -> 0.74957092 | G48: <1.0x = bottom-up is below the run-rate path
A50: Bridge: 2026 run-rate mix (est., $B) -> 2030 (multiple per scenario; CAGR on Base)
A51: Segment | B51: 2026 RR est. | C51: Bear x | D51: Base x | E51: Bull x | F51: Custom x | G51: CAGR (Base, 4.33 yrs)
A52: Developers / coding agents | B52: 25 | C52: =IF($B52=0,"n/a",C19/$B52) -> 1.6313472 | D52: =IF($B52=0,"n/a",D19/$B52) -> 4.97952 | E52: =IF($B52=0,"n/a",E19/$B52) -> 9.732096 | F52: =IF($B52=0,"n/a",F19/$B52) -> 4.97952 | G52: =IF($B52=0,"n/a",(D19/$B52)^(1/4.33)-1) -> 0.44881614
A53: Professional seats | B53: 10 | C53: =IF($B53=0,"n/a",C20/$B53) -> 0.729144 | D53: =IF($B53=0,"n/a",D20/$B53) -> 3.564 | E53: =IF($B53=0,"n/a",E20/$B53) -> 9.2664 | F53: =IF($B53=0,"n/a",F20/$B53) -> 3.564 | G53: =IF($B53=0,"n/a",(D20/$B53)^(1/4.33)-1) -> 0.34112201
A54: General KW seats | B54: 1 | C54: =IF($B54=0,"n/a",C21/$B54) -> 1.313004 | D54: =IF($B54=0,"n/a",D21/$B54) -> 5.688 | E54: =IF($B54=0,"n/a",E21/$B54) -> 23.78496 | F54: =IF($B54=0,"n/a",F21/$B54) -> 5.688 | G54: =IF($B54=0,"n/a",(D21/$B54)^(1/4.33)-1) -> 0.49401708
A55: Machine / agent API | B55: 20 | C55: =IF($B55=0,"n/a",C22/$B55) -> 1.26 | D55: =IF($B55=0,"n/a",D22/$B55) -> 3.8 | E55: =IF($B55=0,"n/a",E22/$B55) -> 8.4 | F55: =IF($B55=0,"n/a",F22/$B55) -> 3.8 | G55: =IF($B55=0,"n/a",(D22/$B55)^(1/4.33)-1) -> 0.36112877
A56: Consumer subscriptions | B56: 6 | C56: =IF($B56=0,"n/a",C23/$B56) -> 0.624 | D56: =IF($B56=0,"n/a",D23/$B56) -> 1.6 | E56: =IF($B56=0,"n/a",E23/$B56) -> 4.16 | F56: =IF($B56=0,"n/a",F23/$B56) -> 1.6 | G56: =IF($B56=0,"n/a",(D23/$B56)^(1/4.33)-1) -> 0.11465604
A57: Consumer ads | B57: 0 | C57: =IF($B57=0,"n/a",C24/$B57) -> n/a | D57: =IF($B57=0,"n/a",D24/$B57) -> n/a | E57: =IF($B57=0,"n/a",E24/$B57) -> n/a | F57: =IF($B57=0,"n/a",F24/$B57) -> n/a | G57: =IF($B57=0,"n/a",(D24/$B57)^(1/4.33)-1) -> n/a
A58: Commerce / agentic transactions | B58: 0 | C58: =IF($B58=0,"n/a",C25/$B58) -> n/a | D58: =IF($B58=0,"n/a",D25/$B58) -> n/a | E58: =IF($B58=0,"n/a",E25/$B58) -> n/a | F58: =IF($B58=0,"n/a",F25/$B58) -> n/a | G58: =IF($B58=0,"n/a",(D25/$B58)^(1/4.33)-1) -> n/a
A59: Other | B59: 3 | C59: =IF($B59=0,"n/a",C26/$B59) -> 1.3333333 | D59: =IF($B59=0,"n/a",D26/$B59) -> 2.6666667 | E59: =IF($B59=0,"n/a",E26/$B59) -> 5 | F59: =IF($B59=0,"n/a",F26/$B59) -> 2.6666667 | G59: =IF($B59=0,"n/a",(D26/$B59)^(1/4.33)-1) -> 0.25422701
A60: TOTAL | B60: =SUM(B52:B59) -> 65 | C60: =C27/$B60 -> 1.2666481 | D60: =D27/$B60 -> 3.9910154 | E60: =E27/$B60 -> 8.7340209 | F60: =F27/$B60 -> 3.9910154 | G60: =(D27/$B60)^(1/4.33)-1 -> 0.37663351 | H60: 2026 mix is our estimate from disclosed run-rates (blue = editable)
A62: What you need to believe (targets vs Base structure)
A63: Target revenue 2030 ($B) | B63: input | C63: 350 | D63: 400
A64: Implied $/GW (total) at Base GW | C64: =C$63/$D$33 -> 21.875 | D64: =D$63/$D$33 -> 25 | G64: target / Base GW
A65: Implied GW at $/GW = | B65: 35 | C65: =C$63/$B65 -> 10 | D65: =D$63/$B65 -> 11.428571 | G65: the deck's $35B/GW assumption (editable)
A66: Implied GW at Base $/GW | C66: =C$63/$D$35 -> 25.942837 | D66: =D$63/$D$35 -> 29.648956
A67: Required uplift on enterprise engines vs Base | C67: =(C$63-($D$27-$D$28))/$D$28 -> 1.3745989 | D67: =(D$63-($D$27-$D$28))/$D$28 -> 1.5813677 | G67: consumer + other held at Base
A68: ...if only developer spend/salary moves | C68: =Inputs!$E$17*(1+(C67-1)*$D$28/$D$19) -> 0.22459482 | D68: =Inputs!$E$17*(1+(D67-1)*$D$28/$D$19) -> 0.27680869 | G68: vs Base ratio on Inputs
A69: ...if only machine-API automated share moves | C69: =Inputs!$E$29*(1+(C67-1)*$D$28/$D$22) -> 0.21918947 | D69: =Inputs!$E$29*(1+(D67-1)*$D$28/$D$22) -> 0.28497895
A70: ...if only professional-seat penetration moves | C70: =Inputs!$E$14*(1+(C67-1)*$D$28/$D$20) -> 1.5937374 | D70: =Inputs!$E$14*(1+(D67-1)*$D$28/$D$20) -> 2.2250505 | G70: >100% = impossible
A71: Target as % of global enterprise AI pool (Base) | C71: =C$63/$D$16 -> 0.46935765 | D71: =D$63/$D$16 -> 0.53640874
A72: Target as % of global labour compensation ($B) = | B72: 65000 | C72: =C$63/$B72 -> 0.0053846154 | D72: =D$63/$B72 -> 0.0061538462 | G72: ~$58T 2025 growing to ~$65T
A73: Target as % of global software spend ($B) = | B73: 2400 | C73: =C$63/$B73 -> 0.14583333 | D73: =D$63/$B73 -> 0.16666667 | G73: Gartner $1.47T 2026 -> ~$2.4T 2030

Sheet Sensitivity
A1: Two-way sensitivities (all constants read the Base column of Inputs; headers in blue are editable)
A3: Revenue ($B) = GW x $/GW
A4: GW \ $B/GW | B4: 8 | C4: 10.5 | D4: 14 | E4: 20 | F4: 28 | G4: 35
A5: 10 | B5: =$A5*B$4 -> 80 | C5: =$A5*C$4 -> 105 | D5: =$A5*D$4 -> 140 | E5: =$A5*E$4 -> 200 | F5: =$A5*F$4 -> 280 | G5: =$A5*G$4 -> 350
A6: 15 | B6: =$A6*B$4 -> 120 | C6: =$A6*C$4 -> 157.5 | D6: =$A6*D$4 -> 210 | E6: =$A6*E$4 -> 300 | F6: =$A6*F$4 -> 420 | G6: =$A6*G$4 -> 525
A7: 20 | B7: =$A7*B$4 -> 160 | C7: =$A7*C$4 -> 210 | D7: =$A7*D$4 -> 280 | E7: =$A7*E$4 -> 400 | F7: =$A7*F$4 -> 560 | G7: =$A7*G$4 -> 700
A8: 25 | B8: =$A8*B$4 -> 200 | C8: =$A8*C$4 -> 262.5 | D8: =$A8*D$4 -> 350 | E8: =$A8*E$4 -> 500 | F8: =$A8*F$4 -> 700 | G8: =$A8*G$4 -> 875
A9: 30 | B9: =$A9*B$4 -> 240 | C9: =$A9*C$4 -> 315 | D9: =$A9*D$4 -> 420 | E9: =$A9*E$4 -> 600 | F9: =$A9*F$4 -> 840 | G9: =$A9*G$4 -> 1050
A11: $/GW of TOTAL capacity ($B) = tokens/GW (1e15) x $/M tokens x inference share x utilisation (Base)
A12: q tokens/GW-yr \ $/M tokens | B12: 0.8 | C12: 1.2 | D12: 1.6 | E12: 2.2 | F12: 3
A13: 12 | B13: =$A13*B$12*Inputs!$E$50*Inputs!$E$51 -> 4.04736 | C13: =$A13*C$12*Inputs!$E$50*Inputs!$E$51 -> 6.07104 | D13: =$A13*D$12*Inputs!$E$50*Inputs!$E$51 -> 8.09472 | E13: =$A13*E$12*Inputs!$E$50*Inputs!$E$51 -> 11.13024 | F13: =$A13*F$12*Inputs!$E$50*Inputs!$E$51 -> 15.1776
A14: 16 | B14: =$A14*B$12*Inputs!$E$50*Inputs!$E$51 -> 5.39648 | C14: =$A14*C$12*Inputs!$E$50*Inputs!$E$51 -> 8.09472 | D14: =$A14*D$12*Inputs!$E$50*Inputs!$E$51 -> 10.79296 | E14: =$A14*E$12*Inputs!$E$50*Inputs!$E$51 -> 14.84032 | F14: =$A14*F$12*Inputs!$E$50*Inputs!$E$51 -> 20.2368
A15: 20 | B15: =$A15*B$12*Inputs!$E$50*Inputs!$E$51 -> 6.7456 | C15: =$A15*C$12*Inputs!$E$50*Inputs!$E$51 -> 10.1184 | D15: =$A15*D$12*Inputs!$E$50*Inputs!$E$51 -> 13.4912 | E15: =$A15*E$12*Inputs!$E$50*Inputs!$E$51 -> 18.5504 | F15: =$A15*F$12*Inputs!$E$50*Inputs!$E$51 -> 25.296
A16: 24 | B16: =$A16*B$12*Inputs!$E$50*Inputs!$E$51 -> 8.09472 | C16: =$A16*C$12*Inputs!$E$50*Inputs!$E$51 -> 12.14208 | D16: =$A16*D$12*Inputs!$E$50*Inputs!$E$51 -> 16.18944 | E16: =$A16*E$12*Inputs!$E$50*Inputs!$E$51 -> 22.26048 | F16: =$A16*F$12*Inputs!$E$50*Inputs!$E$51 -> 30.3552
A17: 32 | B17: =$A17*B$12*Inputs!$E$50*Inputs!$E$51 -> 10.79296 | C17: =$A17*C$12*Inputs!$E$50*Inputs!$E$51 -> 16.18944 | D17: =$A17*D$12*Inputs!$E$50*Inputs!$E$51 -> 21.58592 | E17: =$A17*E$12*Inputs!$E$50*Inputs!$E$51 -> 29.68064 | F17: =$A17*F$12*Inputs!$E$50*Inputs!$E$51 -> 40.4736
A19: OpenAI ads revenue ($B) = free MAU (M) x ads ARPU ($/yr)
A20: free MAU (M) \ $/free user/yr | B20: 15 | C20: 30 | D20: 45 | E20: 60 | F20: 80
A21: 1400 | B21: =$A21*B$20/1000 -> 21 | C21: =$A21*C$20/1000 -> 42 | D21: =$A21*D$20/1000 -> 63 | E21: =$A21*E$20/1000 -> 84 | F21: =$A21*F$20/1000 -> 112
A22: 1900 | B22: =$A22*B$20/1000 -> 28.5 | C22: =$A22*C$20/1000 -> 57 | D22: =$A22*D$20/1000 -> 85.5 | E22: =$A22*E$20/1000 -> 114 | F22: =$A22*F$20/1000 -> 152
A23: 2300 | B23: =$A23*B$20/1000 -> 34.5 | C23: =$A23*C$20/1000 -> 69 | D23: =$A23*D$20/1000 -> 103.5 | E23: =$A23*E$20/1000 -> 138 | F23: =$A23*F$20/1000 -> 184
A25: OpenAI consumer subscriptions ($B) = MAU (M) x paid conversion x Base ARPU x 12
A26: MAU (M) \ paid conversion | B26: 0.04 | C26: 0.06 | D26: 0.08 | E26: 0.1
A27: 1500 | B27: =$A27*B$26*Inputs!$E$36*12/1000 -> 12.96 | C27: =$A27*C$26*Inputs!$E$36*12/1000 -> 19.44 | D27: =$A27*D$26*Inputs!$E$36*12/1000 -> 25.92 | E27: =$A27*E$26*Inputs!$E$36*12/1000 -> 32.4
A28: 2000 | B28: =$A28*B$26*Inputs!$E$36*12/1000 -> 17.28 | C28: =$A28*C$26*Inputs!$E$36*12/1000 -> 25.92 | D28: =$A28*D$26*Inputs!$E$36*12/1000 -> 34.56 | E28: =$A28*E$26*Inputs!$E$36*12/1000 -> 43.2
A29: 2500 | B29: =$A29*B$26*Inputs!$E$36*12/1000 -> 21.6 | C29: =$A29*C$26*Inputs!$E$36*12/1000 -> 32.4 | D29: =$A29*D$26*Inputs!$E$36*12/1000 -> 43.2 | E29: =$A29*E$26*Inputs!$E$36*12/1000 -> 54
A31: Anthropic developer engine ($B) = paid devs (Base: workers x penetration) x spend ($k/dev/yr) x Anthropic share
A32: $k/dev/yr \ Anthropic share | B32: 0.3 | C32: 0.36 | D32: 0.42 | E32: 0.48
A33: 4 | B33: =Inputs!$E$6*Inputs!$E$13*$A33*B$32 -> 36.48 | C33: =Inputs!$E$6*Inputs!$E$13*$A33*C$32 -> 43.776 | D33: =Inputs!$E$6*Inputs!$E$13*$A33*D$32 -> 51.072 | E33: =Inputs!$E$6*Inputs!$E$13*$A33*E$32 -> 58.368
A34: 6 | B34: =Inputs!$E$6*Inputs!$E$13*$A34*B$32 -> 54.72 | C34: =Inputs!$E$6*Inputs!$E$13*$A34*C$32 -> 65.664 | D34: =Inputs!$E$6*Inputs!$E$13*$A34*D$32 -> 76.608 | E34: =Inputs!$E$6*Inputs!$E$13*$A34*E$32 -> 87.552
A35: 9 | B35: =Inputs!$E$6*Inputs!$E$13*$A35*B$32 -> 82.08 | C35: =Inputs!$E$6*Inputs!$E$13*$A35*C$32 -> 98.496 | D35: =Inputs!$E$6*Inputs!$E$13*$A35*D$32 -> 114.912 | E35: =Inputs!$E$6*Inputs!$E$13*$A35*E$32 -> 131.328
A36: 12 | B36: =Inputs!$E$6*Inputs!$E$13*$A36*B$32 -> 109.44 | C36: =Inputs!$E$6*Inputs!$E$13*$A36*C$32 -> 131.328 | D36: =Inputs!$E$6*Inputs!$E$13*$A36*D$32 -> 153.216 | E36: =Inputs!$E$6*Inputs!$E$13*$A36*E$32 -> 175.104
A37: 15 | B37: =Inputs!$E$6*Inputs!$E$13*$A37*B$32 -> 136.8 | C37: =Inputs!$E$6*Inputs!$E$13*$A37*C$32 -> 164.16 | D37: =Inputs!$E$6*Inputs!$E$13*$A37*D$32 -> 191.52 | E37: =Inputs!$E$6*Inputs!$E$13*$A37*E$32 -> 218.88
A39: Professional-seat global pool ($B) = professionals (Base) x penetration x $/seat
A40: penetration \ $/seat/yr | B40: 900 | C40: 1800 | D40: 2700 | E40: 3600
A41: 0.3 | B41: =Inputs!$E$7*$A41*B$40/1000 -> 59.4 | C41: =Inputs!$E$7*$A41*C$40/1000 -> 118.8 | D41: =Inputs!$E$7*$A41*D$40/1000 -> 178.2 | E41: =Inputs!$E$7*$A41*E$40/1000 -> 237.6
A42: 0.45 | B42: =Inputs!$E$7*$A42*B$40/1000 -> 89.1 | C42: =Inputs!$E$7*$A42*C$40/1000 -> 178.2 | D42: =Inputs!$E$7*$A42*D$40/1000 -> 267.3 | E42: =Inputs!$E$7*$A42*E$40/1000 -> 356.4
A43: 0.6 | B43: =Inputs!$E$7*$A43*B$40/1000 -> 118.8 | C43: =Inputs!$E$7*$A43*C$40/1000 -> 237.6 | D43: =Inputs!$E$7*$A43*D$40/1000 -> 356.4 | E43: =Inputs!$E$7*$A43*E$40/1000 -> 475.2
A45: Machine / agent API global pool ($B) = labour pool (Base, $T) x automated share x vendor capture
A46: automated share \ vendor capture | B46: 0.15 | C46: 0.2 | D46: 0.25 | E46: 0.3 | F46: 0.35
A47: 0.05 | B47: =Inputs!$E$28*1000*$A47*B$46 -> 60 | C47: =Inputs!$E$28*1000*$A47*C$46 -> 80 | D47: =Inputs!$E$28*1000*$A47*D$46 -> 100 | E47: =Inputs!$E$28*1000*$A47*E$46 -> 120 | F47: =Inputs!$E$28*1000*$A47*F$46 -> 140
A48: 0.1 | B48: =Inputs!$E$28*1000*$A48*B$46 -> 120 | C48: =Inputs!$E$28*1000*$A48*C$46 -> 160 | D48: =Inputs!$E$28*1000*$A48*D$46 -> 200 | E48: =Inputs!$E$28*1000*$A48*E$46 -> 240 | F48: =Inputs!$E$28*1000*$A48*F$46 -> 280
A49: 0.15 | B49: =Inputs!$E$28*1000*$A49*B$46 -> 180 | C49: =Inputs!$E$28*1000*$A49*C$46 -> 240 | D49: =Inputs!$E$28*1000*$A49*D$46 -> 300 | E49: =Inputs!$E$28*1000*$A49*E$46 -> 360 | F49: =Inputs!$E$28*1000*$A49*F$46 -> 420
A50: 0.2 | B50: =Inputs!$E$28*1000*$A50*B$46 -> 240 | C50: =Inputs!$E$28*1000*$A50*C$46 -> 320 | D50: =Inputs!$E$28*1000*$A50*D$46 -> 400 | E50: =Inputs!$E$28*1000*$A50*E$46 -> 480 | F50: =Inputs!$E$28*1000*$A50*F$46 -> 560
A52: Gross margin on inference = 1 - (compute cost per GW / revenue per GW)
A53: $B revenue/GW \ $B cost/GW-yr | B53: 6 | C53: 8 | D53: 10 | E53: 13.3
A54: 10.5 | B54: =1-B$53/$A54 -> 0.42857143 | C54: =1-C$53/$A54 -> 0.23809524 | D54: =1-D$53/$A54 -> 0.047619048 | E54: =1-E$53/$A54 -> -0.26666667
A55: 13.5 | B55: =1-B$53/$A55 -> 0.55555556 | C55: =1-C$53/$A55 -> 0.40740741 | D55: =1-D$53/$A55 -> 0.25925926 | E55: =1-E$53/$A55 -> 0.014814815
A56: 20 | B56: =1-B$53/$A56 -> 0.7 | C56: =1-C$53/$A56 -> 0.6 | D56: =1-D$53/$A56 -> 0.5 | E56: =1-E$53/$A56 -> 0.335
A57: 28 | B57: =1-B$53/$A57 -> 0.78571429 | C57: =1-C$53/$A57 -> 0.71428571 | D57: =1-D$53/$A57 -> 0.64285714 | E57: =1-E$53/$A57 -> 0.525
A58: 35 | B58: =1-B$53/$A58 -> 0.82857143 | C58: =1-C$53/$A58 -> 0.77142857 | D58: =1-D$53/$A58 -> 0.71428571 | E58: =1-E$53/$A58 -> 0.62

Sheet Sources
A1: Data anchors and sources (as of 24-Sep-2026; several are press summaries of company disclosures - flagged 'secondary')
A3: Data point | B3: Date | C3: Source | D3: URL
A4: OpenAI annualised revenue run-rate >$40B; enterprise >50% of mix | B4: Aug-2026 | C4: press (enterprisedna.co / valueaddvc.com summaries of company statements) | D4: https://enterprisedna.co/resources/news/openai-enterprise-revenue-overtakes-consumer-40-billion-arr-2026/
A5: ChatGPT ~1B MAU (Jun-26), ~1B WAU (Jul-26); >50M consumer subs; 9M paying business users; 7M enterprise seats | B5: Jul/Aug-2026 | C5: demandsage / secondtalent (secondary) | D5: https://www.demandsage.com/chatgpt-statistics/
A6: OpenAI forecasts 2030 revenue >$280B; consumer/enterprise ~50/50 by 2030 | B6: 20-Feb-2026 | C6: Bloomberg | D6: https://www.bloomberg.com/news/articles/2026-02-20/openai-forecasts-its-revenue-will-top-280-billion-in-2030
A7: OpenAI ads plan: $2.5B 2026, $11B 2027, $25B 2028, $53B 2029, $100B 2030 | B7: 09-Apr-2026 | C7: Axios | D7: https://axios.com/2026/04/09/openai-100-billion-in-ad-revenue
A8: ChatGPT ads: launched 9-Feb-2026 (US Free + Go); $1B run-rate in <200 days; ~$60 CPM | B8: 2026 | C8: press (secondary) | D8: https://explainx.ai/blog/openai-advertise-in-chatgpt-ads-launch-july-2026
A9: OpenAI API 15B tokens/min; Codex 2M+ weekly users | B9: Mar-2026 | C9: OpenAI | D9: https://openai.com/index/a-business-that-scales-with-the-value-of-intelligence/
A10: OpenAI compute: 0.2GW (2023) -> 1.9GW (2025) while run-rate $2B -> $20B (~$10B/GW) | B10: 2025 | C10: MBI Deep Dives citing OpenAI | D10: https://www.mbi-deepdives.com/oai-breakeven/
A11: OpenAI 30GW target by 2030; compute spend ~$600B -> ~$750B through 2030 | B11: 2026 | C11: WSJ / DCD (secondary) | D11: https://www.datacenterdynamics.com/en/news/openai-cuts-projected-compute-spend-to-600bn-by-2030-report/
A12: OpenAI-Nvidia 10GW LOI; AMD 6GW; Broadcom 10GW; Stargate 10GW (8GW+ secured) | B12: 2025-26 | C12: OpenAI | D12: https://openai.com/index/openai-nvidia-systems-partnership/
A13: Oracle-OpenAI $300B / 5 yrs / 4.5GW (~$13.3B per GW-year) | B13: Jul/Sep-2025 | C13: The Register | D13: https://www.theregister.com/2025/07/22/openai_oracle_gpus/
A14: Anthropic run-rate $65B (end-Jul-26); $47B mid-May; $9B end-2025 | B14: 17-Aug-2026 | C14: Bloomberg / TechCrunch / Axios | D14: https://techcrunch.com/2026/08/17/anthropics-annualized-revenue-surges-to-65b/
... A35: Superforecasters: OpenAI+Anthropic combined 2030 run-rate median $300B; 34% prob >$400B; 18% prob <$100B | B35: 2026 | C35: Forecasting Research Institute | D35: https://forecastingresearch.substack.com/p/will-the-ai-boom-continue-forecasting
